keras2vec/__init__.py
keras2vec/data_generator.py
keras2vec/document.py
keras2vec/encoder.py
keras2vec/keras2vec.py
Keras2Vec-0.1.1.dist-info/LICENSE
Keras2Vec-0.1.1.dist-info/METADATA
Keras2Vec-0.1.1.dist-info/WHEEL
Keras2Vec-0.1.1.dist-info/top_level.txt
Keras2Vec-0.1.1.dist-info/RECORD
