Metadata-Version: 2.1
Name: Keras2Vec
Version: 0.1.1
Summary: Keras implementation of Doc2Vec
Home-page: https://github.com/jdk514/keras2vec
Author: Joel Klein
Author-email: jdk51405@gmail.com
License: UNKNOWN
Project-URL: Documentation, https://keras2vec.readthedocs.io/en/latest/index.html
Platform: UNKNOWN
Classifier: Programming Language :: Python :: 3.6
Classifier: License :: OSI Approved :: MIT License
Classifier: Operating System :: OS Independent
Requires-Python: >=3.6
Requires-Dist: tensorflow (>=1.14.0)
Requires-Dist: keras (>=2.2.4)
Requires-Dist: numpy (>=1.16.4)
